README.md
requirements.txt
botrun_ask_folder/__init__.py
botrun_ask_folder/botrun_ask_folder.py
botrun_ask_folder/botrun_ask_folder_logger.py
botrun_ask_folder/botrun_drive_manager.py
botrun_ask_folder/botrun_reader.py
botrun_ask_folder/botrun_translate_all_pages.py
botrun_ask_folder/constants.py
botrun_ask_folder/create_qdrant_collection.py
botrun_ask_folder/drive_download.py
botrun_ask_folder/drive_download_metadata.py
botrun_ask_folder/drive_list_files.py
botrun_ask_folder/drive_upload.py
botrun_ask_folder/embeddings_to_qdrant.py
botrun_ask_folder/emoji_progress_bar.py
botrun_ask_folder/find_unprocessed_pdf_or_office_files.py
botrun_ask_folder/generate_pages_html.py
botrun_ask_folder/get_rag_reference.py
botrun_ask_folder/google_drive_service.py
botrun_ask_folder/import_rag_plus.py
botrun_ask_folder/is_cached.py
botrun_ask_folder/is_text_file.py
botrun_ask_folder/log_handler.py
botrun_ask_folder/md5_base64.py
botrun_ask_folder/pipeline_drive_query.py
botrun_ask_folder/process_folder_from_restapi.py
botrun_ask_folder/process_folder_job.py
botrun_ask_folder/query_page_range.py
botrun_ask_folder/query_qdrant.py
botrun_ask_folder/query_qdrant_keyword.py
botrun_ask_folder/query_qdrant_rerank.py
botrun_ask_folder/remove_qdrant_collection.py
botrun_ask_folder/run_pdf_to_img.py
botrun_ask_folder/run_split_txts.py
botrun_ask_folder/safe_join.py
botrun_ask_folder/split_txts.py
botrun_ask_folder/status_tracker.py
botrun_ask_folder/translations.py
botrun_ask_folder/update_files_from_drive.py
botrun_ask_folder/fast_api/README.md
botrun_ask_folder/fast_api/__init__.py
botrun_ask_folder/fast_api/doc_api.py
botrun_ask_folder/fast_api/drive_api.py
botrun_ask_folder/fast_api/jwt_util.py
botrun_ask_folder/fast_api/main.py
botrun_ask_folder/fast_api/queue_api.py
botrun_ask_folder/fast_api/router_botrun_ask_folder.py
botrun_ask_folder/fast_api/router_linebot.py
botrun_ask_folder/fast_api/storage_api.py
botrun_ask_folder/fast_api/static/static.py
botrun_ask_folder-5.9.11.dist-info/METADATA
botrun_ask_folder-5.9.11.dist-info/WHEEL
botrun_ask_folder-5.9.11.dist-info/entry_points.txt
botrun_ask_folder-5.9.11.dist-info/RECORD
