Metadata-Version: 2.4
Name: botrun_ask_folder
Version: 5.9.11
Requires-Dist: aiohttp
Requires-Dist: botrun-hatch>=5.3.141
Requires-Dist: botrun-litellm>=0.2.5
Requires-Dist: chardet
Requires-Dist: cryptography
Requires-Dist: deepdiff
Requires-Dist: docx2txt
Requires-Dist: fastapi
Requires-Dist: functions-framework>=3.0.0
Requires-Dist: google-api-python-client
Requires-Dist: google-auth
Requires-Dist: google-cloud-firestore
Requires-Dist: google-cloud-run
Requires-Dist: google-cloud-storage
Requires-Dist: litellm
Requires-Dist: lxml
Requires-Dist: openpyxl
Requires-Dist: pandas
Requires-Dist: pdfplumber>=0.11.3
Requires-Dist: pylightxl
Requires-Dist: pymupdf
Requires-Dist: pypdf2
Requires-Dist: python-docx
Requires-Dist: python-multipart>=0.0.20
Requires-Dist: python-pptx
Requires-Dist: pytz
Requires-Dist: qdrant-client
Requires-Dist: starlette>=0.46.1
Requires-Dist: uvicorn>=0.34.2
Requires-Dist: xlrd
